pysciduct/__init__.py
pysciduct/exceptions.py
pysciduct/file.py
pysciduct/job.py
pysciduct/sciduct.py
pysciduct/session.py
pysciduct-0.1.0.dist-info/LICENSE
pysciduct-0.1.0.dist-info/METADATA
pysciduct-0.1.0.dist-info/WHEEL
pysciduct-0.1.0.dist-info/top_level.txt
pysciduct-0.1.0.dist-info/RECORD
