Metadata-Version: 2.1
Name: pysciduct
Version: 0.1.0
Summary: Python wrapper classes for SciDuct api.
Home-page: https://github.com/NSSAC/pysciduct.git
Author: Matthew Wong
Author-email: mttwong@vt.edu
License: Apache License 2.0
Platform: UNKNOWN
Requires-Dist: requests
Requires-Dist: pyjwt
Requires-Dist: cryptography
Requires-Dist: jsonschema
